pystandups/__init__.py
pystandups/cli.py
pystandups/lib.py
pystandups-0.4.7.dist-info/entry_points.txt
pystandups-0.4.7.dist-info/WHEEL
pystandups-0.4.7.dist-info/METADATA
pystandups-0.4.7.dist-info/RECORD
