Metadata-Version: 2.1
Name: pystandups
Version: 0.4.7
Summary: A command line utility for working with daily standups.
Home-page: https://github.com/metov/pystandups
Author: Azat Akhmetov
Requires-Python: >=3.6,<4.0
Classifier: Programming Language :: Python :: 3
Classifier: Programming Language :: Python :: 3.10
Classifier: Programming Language :: Python :: 3.6
Classifier: Programming Language :: Python :: 3.7
Classifier: Programming Language :: Python :: 3.8
Classifier: Programming Language :: Python :: 3.9
Requires-Dist: coloredlogs
Requires-Dist: dictdiffer
Requires-Dist: docopt
Requires-Dist: openeditor (>=0.3.1,<0.4.0)
Requires-Dist: questionary
Requires-Dist: tabulate
Requires-Dist: xdg
Project-URL: Repository, https://github.com/metov/pystandups
